gbp_webhook-2.0.0.dist-info/METADATA
gbp_webhook-2.0.0.dist-info/WHEEL
gbp_webhook-2.0.0.dist-info/entry_points.txt
gbp_webhook/__init__.py
gbp_webhook/app.py
gbp_webhook/cli.py
gbp_webhook/handlers.py
gbp_webhook/py.typed
gbp_webhook/server.py
gbp_webhook/systemd.py
gbp_webhook/templates/gbp-webhook.conf
gbp_webhook/templates/gbp-webhook.service
gbp_webhook/templates/nginx.conf
gbp_webhook/types.py
gbp_webhook/utils.py
gbp_webhook-2.0.0.dist-info/RECORD
