Metadata-Version: 2.1
Name: gbp-webhook
Version: 2.0.0
Summary: gbp-notifications webhook server
Author-Email: Albert Hopkins <marduk@letterboxes.org>
License: GPL3+
Project-URL: homepage, https://github.com/enku/gbp-webhook
Project-URL: repository, https://github.com/enku/gbp-webhook
Requires-Python: >=3.12
Requires-Dist: flask>=3.1.0
Requires-Dist: pygobject>=3.50.0
Requires-Dist: gunicorn>=23.0.0
Requires-Dist: jinja2>=3.1.6
Requires-Dist: gbpcli>=2.5.0
Requires-Dist: yarl>=1.20.1
